makiki/__init__.py
makiki/cli.py
makiki/database.py
makiki/documentation.py
makiki/exception.py
makiki/executor.py
makiki/http.py
makiki/monkey.py
makiki/queue.py
makiki/redis.py
makiki/schema.py
makiki/templates/gunicorn_config.py.jinja
makiki/templates/requirements.txt.jinja
makiki/templates/setup.py.jinja
makiki/templates/app/__init__.py.jinja
makiki/templates/app/config.py.jinja
makiki/templates/app/server.py.jinja
makiki/templates/app/urls.py.jinja
makiki/templates/app/handler/__init__.py.jinja
makiki/templates/app/handler/hello.py.jinja
makiki/templates/app/models/__init__.py.jinja
makiki-0.2.13.dist-info/DESCRIPTION.rst
makiki-0.2.13.dist-info/METADATA
makiki-0.2.13.dist-info/RECORD
makiki-0.2.13.dist-info/WHEEL
makiki-0.2.13.dist-info/entry_points.txt
makiki-0.2.13.dist-info/metadata.json
makiki-0.2.13.dist-info/top_level.txt
