Metadata-Version: 2.0
Name: makiki
Version: 0.2.13
Summary: Web service utils and generator.
Home-page: http://github.com/faith0811/makiki
Author: Wang Yanqing
Author-email: me@oreki.moe
License: MIT
Keywords: Web,Python,Python3,utility
Platform: UNKNOWN
Classifier: Development Status :: 4 - Beta
Classifier: Intended Audience :: Developers
Classifier: Environment :: Console
Classifier: License :: OSI Approved :: MIT License
Classifier: Programming Language :: Python
Classifier: Programming Language :: Python :: 3
Classifier: Programming Language :: Python :: 3.2
Classifier: Programming Language :: Python :: 3.3
Classifier: Programming Language :: Python :: 3.4
Classifier: Programming Language :: Python :: 3.5
Classifier: Programming Language :: Python :: 3.6
Classifier: Topic :: Utilities
Requires-Dist: Jinja2 (>=2.8.1)
Requires-Dist: blinker (>=1.4)
Requires-Dist: gevent (>=1.2)
Requires-Dist: gunicorn (>=19.0)
Requires-Dist: hug (==2.2.0)
Requires-Dist: psycogreen (>=1.0.0)
Requires-Dist: psycopg2 (>=2.6.2)
